[
    {
      "name":"Pikachu",
      "typePokemon":"Electrico",
      "damage":112,
      "hp":99
    },
     {
      "name":"Squitle",
      "typePokemon":"Agua",
      "damage":94,
      "hp":112
    },
     {
      "name":"Jigglypugg",
      "typePokemon":"Hada",
      "damage":80,
      "hp":210
    },
     {
      "name":"Charmander",
      "typePokemon":"Fuego",
      "damage":116,
      "hp":105
    },
     {
      "name":"Bulbasaur",
      "typePokemon":"Planta",
      "damage":118,
      "hp":113
    },
    {
      "name":"Snorlax",
      "typePokemon":"Normal",
      "damage":190,
      "hp":272
    },
    {
      "name":"Mewtwo",
      "typePokemon":"Psiquico",
      "damage":300,
      "hp":3000
    },
    {
      "name":"Ekans",
      "typePokemon":"Veneno",
      "damage":150,
      "hp":99
    }
    ]